posturner/__init__.py
posturner/set.py
posturner-0.1.13.dist-info/METADATA
posturner-0.1.13.dist-info/WHEEL
posturner-0.1.13.dist-info/top_level.txt
posturner-0.1.13.dist-info/RECORD
