Metadata-Version: 2.4
Name: posturner
Version: 0.1.13
Summary: transfrom different language pos tags to universal pos tags.
Home-page: https://gitlab.com/Simirror/posturner
Author: Feliks Peegel
Author-email: felikspeegel@outlook.com
Classifier: Programming Language :: Python :: 3
Classifier: License :: OSI Approved :: MIT License
Requires-Python: >=3.6
Dynamic: author
Dynamic: author-email
Dynamic: classifier
Dynamic: description
Dynamic: description-content-type
Dynamic: home-page
Dynamic: requires-python
Dynamic: summary
